{
  "id": "VCKolD1-ab84YIxODeMGob9A2",
  "advancedConfiguration": true,
   "BlueprintId": 0,
  "allowAdvancedCustomization": true,
  "forceAdvancedCustomization": false,
  "defaultPageToken": "cs_overview",
  "defaultRdpSoundConfig": "Disabled",
  "fullscreenLandingState": null,
  "defaultPageOptions": [
    { "id": "cs_overview", "name": "Overview" },
    { "id": "cs_vm_list", "name": "VM List" }
  ],
  "advancedGeneralSettings": {
    "defaultTabId": "CTKolD1-ab84YIxODeMGob9A2",
    "slackSettings": {
      "isEnabled": null,
      "channelId": null
    }
  },
  "tabs": [
    {
      "type": 221,
      "id": "CTKolD1-ab84YIxODeMGob9A2",
      "name": "",
      "order": 0,
      "visible": true,
      "location": null,
      "markupTemplate": "",
      "lastUpdateTime": "Sun, 28 Feb 2016 06:15:33 GMT"
    },
    {
      "type": 223,
      "id": "CTR-GlgOl2FOP8DXqKgJEpnw2",
      "name": "Overview1",
      "order": 0,
      "visible": true,
      "location": null,
      "markupTemplate": "<div class=\"cs-viewer-page\"><div class=\"cs-viewer-page-content\"><div class=\"cs-viewer-page-content-left\"><div class=\"cs-viewer-page-main-title\">{{Name}}</div><div class=\"cs-viewer-page-description\">{{Description}}</div><cs-viewer-start-button></cs-viewer-start-button></div><div class=\"cs-viewer-page-content-right\"></div></div></div>",
      "lastUpdateTime": "Sun, 10 Jan 2021 06:15:19 GMT"
    },
    {
      "type": 229,
      "id": "CTitsTtiUS27hEsHcVZcZsxw2",
      "name": "VM List",
      "order": 1,
      "visible": true,
      "location": null,
      "showCredentials": true,
      "lastUpdateTime": "Sun, 10 Jan 2021 06:15:19 GMT"
    }
  ],
  "defaultTabsContent": [],
  "slackSettingsContent": null,
  "brandingData": null,
  "endUserLogin": null,
  "guidedJourney": null
}
